LICENSE
README.md
setup.py
certbot_dns_conoha/__init__.py
certbot_dns_conoha/conoha_dns_v1.py
certbot_dns_conoha/dns_conoha.py
certbot_dns_conoha.egg-info/PKG-INFO
certbot_dns_conoha.egg-info/SOURCES.txt
certbot_dns_conoha.egg-info/dependency_links.txt
certbot_dns_conoha.egg-info/entry_points.txt
certbot_dns_conoha.egg-info/requires.txt
certbot_dns_conoha.egg-info/top_level.txt